more_polars/__init__.py
more_polars/column_expr.py
more_polars/column_helpers.py
more_polars/more_polars.py
more_polars-0.3.0.dist-info/WHEEL
more_polars-0.3.0.dist-info/METADATA
more_polars-0.3.0.dist-info/RECORD
