Metadata-Version: 2.1
Name: more-polars
Version: 0.3.0
Summary: 
Author: Todd Iverson
Author-email: Tiverson@winona.edu
Requires-Python: >=3.7
Classifier: Programming Language :: Python :: 3
Classifier: Programming Language :: Python :: 3.7
Classifier: Programming Language :: Python :: 3.8
Classifier: Programming Language :: Python :: 3.9
Classifier: Programming Language :: Python :: 3.10
Classifier: Programming Language :: Python :: 3.11
Requires-Dist: composable (>=0.5.4)
Requires-Dist: polars (>=0.14.26)
